pbi_cli/__init__.py
pbi_cli/auth.py
pbi_cli/cli.py
pbi_cli/powerbi/__init__.py
pbi_cli/powerbi/admin.py
pbi_cli/powerbi/app.py
pbi_cli/powerbi/base.py
pbi_cli/powerbi/io.py
pbi_cli/powerbi/report.py
pbi_cli/web.py
pbi_cli-0.1.0.dist-info/METADATA
pbi_cli-0.1.0.dist-info/WHEEL
pbi_cli-0.1.0.dist-info/entry_points.txt
pbi_cli-0.1.0.dist-info/RECORD
